Paquete_Divsas/proyecto_divisas.py
Paquete_Divsas/unit_test.py
paquete_divisas_python-0.0.1.dist-info/METADATA
paquete_divisas_python-0.0.1.dist-info/WHEEL
paquete_divisas_python-0.0.1.dist-info/licenses/LICENSE
paquete_divisas_python-0.0.1.dist-info/RECORD
