Metadata-Version: 2.1
Name: Paquete_Divisas_Python
Version: 0.0.1
Summary: Proyecto para graficar pares de divisas de forma sencilla
Project-URL: Homepage, https://github.com/JavierCuesta12/Divisas_Python
Project-URL: Bug Tracker, https://github.com/JavierCuesta12/Divisas_Python/issues
Author-email: javiercuesta <javiercuesta660@gmail.com>
License: MIT License
License-File: LICENSE
Classifier: License :: OSI Approved :: MIT License
Classifier: Operating System :: OS Independent
Classifier: Programming Language :: Python :: 3
Requires-Python: >=3.9
